vedlibrary/__init__.py
vedlibrary/project.py
vedlibrary-0.1.dist-info/METADATA
vedlibrary-0.1.dist-info/WHEEL
vedlibrary-0.1.dist-info/top_level.txt
vedlibrary-0.1.dist-info/RECORD
